{
  "name": "room2",
  "background": "/rooms/img/room_2/view/room_2-vestiaire.webp",
  "riddle": {
    "question": "Cette porte est verrouillée par un cadenas à six chiffres.",
    "answer": "221444",
    "congratulation":["On prévoit de vendre 2'668 casques sur l'année N à CHF 83 par pièce.", "Le chiffre d'affaires prévisionnel correspond à 2'668 X 83 = 221'444"]
  },
  "areas": [
    {
        "name":"Sortie vestiaire",
        "class":"zone riddle",
        "x":72,
        "y":36,
        "width":2,
        "height":36
    },
    {
      "name": "Club de golf",
      "class": "zone innerRoom",
      "image": "/rooms/img/room_2/items/room_2-golf.webp",
      "innerRoom": {
        "background": "/rooms/img/room_2/view/room_2-club_golf.webp",
        "areas": [
          {
            "name": "sortir",
            "class": "zone out",
            "x": 0,
            "y": 0,
            "width": 100,
            "height": 23
          }
        ]
      },
      "x": 61,
      "y": 67,
      "width": 9,
      "height": 18
    },
    {
      "name": "Maillot 4",
      "class": "item",
      "takeable": true,
      "image": "/rooms/img/room_2/items/room_2-maillot_4.webp",
      "image_zoom": "/rooms/img/room_2/items/room_2-maillot_4-zoom.webp",
      "x": 59,
      "y": 47,
      "width": 7,
      "height": 10
    },
    {
      "name": "Une veste",
      "class": "item",
      "takeable": false,
      "image": "/rooms/img/room_2/items/room_2-veste.webp",
      "description": "Cette veste ne présente aucun intérêt...",
      "x": 37,
      "y": 45,
      "width": 4,
      "height": 19
    },
    {
      "name": "Des balles",
      "class": "item",
      "takeable": false,
      "image": "/rooms/img/room_2/items/room_2-balles.webp",
      "description": "J'aime pas les jeux de balles!",
      "x": 6,
      "y": 72,
      "width": 10,
      "height": 8
    },
    {
      "name": "Un papier avec un code",
      "class": "item",
      "takeable": true,
      "image": "/rooms/img/room_2/items/room_2-papier_enigme_2.webp",
      "image_zoom": "/rooms/img/room_2/items/room_2-papier_enigme_2-zoom.webp",
      "x": 19,
      "y": 72,
      "width": 4,
      "height": 3
    },
    {
      "name": "Un papier avec un indice",
      "class": "item",
      "takeable": true,
      "image": "/rooms/img/room_2/items/room_2-papier_enigme.webp",
      "image_zoom": "/rooms/img/room_2/items/room_2-papier_enigme-zoom.webp",
      "x": 45,
      "y": 67,
      "width": 4,
      "height": 3
    },
    {
        "name": "Un classeur bleu",
        "class": "item",
        "takeable": true,
        "image": "/rooms/img/room_2/items/room_2-classeur.webp",
        "image_zoom": "/rooms/img/room_2/items/room_2-classeur-zoom.webp",
        "x": 20,
        "y": 78,
        "width": 10,
        "height": 3
      },
      {
        "name": "Des trucs",
        "class": "item",
        "takeable": false,
        "image": "/rooms/img/room_2/items/room_2-des_trucs.webp",
        "description": "Aucune idée de leur utilité... laissons ça ici!",
        "x": 40,
        "y": 77,
        "width": 10,
        "height": 6
      },
      {
        "name": "Des chaussures",
        "class": "item",
        "takeable": false,
        "image": "/rooms/img/room_2/items/room_2-chaussures.webp",
        "description": "Mon dieu! Quelle odeur...",
        "x": 41,
        "y": 87,
        "width": 8,
        "height": 6
      }
  ]
}
